nbodypy/Nbody.py
nbodypy/__init__.py
nbodypy/dynamics.py
nbodypy/plotlib.py
nbodypy/RCTBP/RCTBP.py
nbodypy/RCTBP/__init__.py
nbodypy-0.2.1.dist-info/LICENSE
nbodypy-0.2.1.dist-info/METADATA
nbodypy-0.2.1.dist-info/WHEEL
nbodypy-0.2.1.dist-info/top_level.txt
nbodypy-0.2.1.dist-info/RECORD
