Metadata-Version: 2.1
Name: nbodypy
Version: 0.2.1
Summary: Package for N-body problem, and RC3BP
Home-page: https://plmlab.math.cnrs.fr/mchupin/nbody
Author: Maxime Chupin
Author-email: chupin@ceremade.dauphine.fr
License: GNU GPLv3
Platform: UNKNOWN
Requires-Python: >=3.6
Requires-Dist: numpy
Requires-Dist: matplotlib
Requires-Dist: scipy
